djenerator/__init__.py
djenerator/djenerator.py
djenerator/fields_generator.py
djenerator/generate_test_data.py
djenerator/model_reader.py
djenerator/utility.py
djenerator/values_generator.py
djenerator/management/__init__.py
djenerator/management/commands/__init__.py
djenerator/management/commands/jendb.py
djenerator/management/commands/jenerate.py
djenerator-1.0.1.dist-info/DESCRIPTION.rst
djenerator-1.0.1.dist-info/METADATA
djenerator-1.0.1.dist-info/RECORD
djenerator-1.0.1.dist-info/WHEEL
djenerator-1.0.1.dist-info/metadata.json
djenerator-1.0.1.dist-info/top_level.txt
