Metadata-Version: 2.0
Name: djenerator
Version: 1.0.1
Summary: A simple app for generating test data for a given django models description.
Home-page: https://github.com/mostafa-mahmoud/djenerator
Author: Mostafa M. Mohamed
Author-email: mostafa.amin93@gmail.com
License: MIT
Download-URL: https://github.com/mostafa-mahmoud/djenerator/archive/v1.0.1.tar.gz
Platform: UNKNOWN
Classifier: Development Status :: 4 - Beta
Classifier: Environment :: Web Environment
Classifier: Framework :: Django :: 1.10
Classifier: Intended Audience :: Developers
Classifier: License :: OSI Approved :: MIT License
Classifier: Operating System :: OS Independent
Classifier: Programming Language :: Python :: 2.7
Classifier: Topic :: Software Development :: Libraries :: Python Modules
Requires-Dist: django (>=1.10)
